{
    "audio_path": "dev-clean\\LibriSpeech\\dev-clean\\1462\\170138\\1462-170138-0024.flac",
    "text": "<|startoftext|> HE LEANED FORWARD AND BEAMED FELICITATIONS AS WARMLY AS MAINHALL HIMSELF WHEN AT THE END OF THE PLAY SHE CAME AGAIN AND AGAIN BEFORE THE CURTAIN PANTING A LITTLE AND FLUSHED HER EYES DANCING AND HER EAGER NERVOUS LITTLE MOUTH TREMULOUS WITH EXCITEMENT <|endoftext|>",
    "tokens": [
        50255,
        13909,
        12509,
        1565,
        1961,
        7473,
        39743,
        5357,
        9348,
        2390,
        1961,
        376,
        3698,
        2149,
        2043,
        18421,
        7054,
        11837,
        5805,
        56,
        7054,
        8779,
        1268,
        39,
        7036,
        45909,
        50,
        37738,
        42099,
        5161,
        3336,
        23578,
        3963,
        3336,
        28180,
        48052,
        327,
        10067,
        36218,
        1268,
        5357,
        36218,
        1268,
        38331,
        3336,
        327,
        4261,
        30339,
        350,
        8643,
        2751,
        317,
        406,
        22470,
        2538,
        5357,
        9977,
        27143,
        1961,
        24906,
        412,
        43335,
        360,
        20940,
        2751,
        5357,
        24906,
        412,
        4760,
        1137,
        399,
        1137,
        53,
        20958,
        406,
        22470,
        2538,
        337,
        2606,
        4221,
        309,
        40726,
        6239,
        20958,
        13315,
        7788,
        34,
        2043,
        12529,
        50256
    ],
    "metadata": {
        "speaker_id": "1462",
        "chapter_id": "170138",
        "file_id": "1462-170138-0024"
    }
}