{
    "audio_path": "dev-clean\\LibriSpeech\\dev-clean\\1988\\148538\\1988-148538-0008.flac",
    "text": "THE AMERICANS IN THEIR INTERCOURSE WITH STRANGERS APPEAR IMPATIENT OF THE SMALLEST CENSURE AND INSATIABLE OF PRAISE",
    "tokens": [
        10970,
        32617,
        2149,
        15037,
        3268,
        47278,
        23255,
        34,
        11698,
        5188,
        13315,
        19269,
        15567,
        4877,
        3486,
        11401,
        1503,
        30023,
        1404,
        28495,
        3963,
        3336,
        9447,
        7036,
        6465,
        327,
        16938,
        11335,
        5357,
        29194,
        1404,
        3539,
        19146,
        3963,
        350,
        3861,
        24352
    ],
    "metadata": {
        "speaker_id": "1988",
        "chapter_id": "148538",
        "file_id": "1988-148538-0008"
    }
}