{
    "audio_path": "dev-clean\\LibriSpeech\\dev-clean\\2035\\152373\\2035-152373-0017.flac",
    "text": "<|startoftext|> SAINT MOLING SURVIVED HIM THREE YEARS AND SAINT ADAMNAN SO INTIMATELY CONNECTED WITH HIS REIGN TEN YEARS <|endoftext|>",
    "tokens": [
        50255,
        4090,
        12394,
        337,
        3535,
        2751,
        41016,
        53,
        3824,
        1961,
        45909,
        48697,
        32914,
        50,
        5357,
        14719,
        12394,
        5984,
        2390,
        45,
        1565,
        12809,
        17828,
        3955,
        1404,
        30943,
        7102,
        48842,
        1961,
        13315,
        33700,
        4526,
        16284,
        309,
        1677,
        32914,
        50,
        50256
    ],
    "metadata": {
        "speaker_id": "2035",
        "chapter_id": "152373",
        "file_id": "2035-152373-0017"
    }
}