{
    "audio_path": "dev-clean\\LibriSpeech\\dev-clean\\2412\\153954\\2412-153954-0020.flac",
    "text": "<|startoftext|> AGAIN THERE WAS A VERY OLD CARRIAGE WHOSE WHEELS IN SPITE OF RUST AND DECAY I COULD SEE HAD BEEN DESIGNED ORIGINALLY FOR IRON RAILS <|endoftext|>",
    "tokens": [
        50255,
        4760,
        29833,
        34702,
        21725,
        317,
        29550,
        440,
        11163,
        17368,
        49,
        3539,
        8264,
        7655,
        14058,
        7655,
        36,
        37142,
        3268,
        6226,
        12709,
        3963,
        371,
        7759,
        5357,
        27196,
        4792,
        314,
        327,
        24010,
        31107,
        367,
        2885,
        9348,
        1677,
        22196,
        16284,
        1961,
        43901,
        1268,
        19807,
        7473,
        14826,
        1340,
        17926,
        45484,
        50256
    ],
    "metadata": {
        "speaker_id": "2412",
        "chapter_id": "153954",
        "file_id": "2412-153954-0020"
    }
}