{
    "audio_path": "dev-clean\\LibriSpeech\\dev-clean\\2412\\153948\\2412-153948-0004.flac",
    "text": "<|startoftext|> SHEEP AND CATTLE WERE INTRODUCED AND BRED WITH EXTREME RAPIDITY MEN TOOK UP THEIR FIFTY THOUSAND OR ONE HUNDRED THOUSAND ACRES OF COUNTRY GOING INLAND ONE BEHIND THE OTHER TILL IN A FEW YEARS THERE WAS NOT AN ACRE BETWEEN THE SEA AND THE FRONT RANGES WHICH WAS NOT TAKEN UP AND STATIONS EITHER FOR SHEEP OR CATTLE WERE SPOTTED ABOUT AT INTERVALS OF SOME TWENTY OR THIRTY MILES OVER THE WHOLE COUNTRY <|endoftext|>",
    "tokens": [
        50255,
        9693,
        35238,
        5357,
        327,
        35455,
        370,
        9338,
        3268,
        5446,
        3727,
        9598,
        1961,
        5357,
        11177,
        1961,
        13315,
        27489,
        2200,
        11682,
        371,
        2969,
        2389,
        9050,
        41597,
        5390,
        11380,
        15958,
        47278,
        376,
        5064,
        9936,
        2320,
        20958,
        6981,
        6375,
        16329,
        41041,
        7707,
        1961,
        2320,
        20958,
        6981,
        7125,
        19535,
        3963,
        31404,
        40405,
        10351,
        2751,
        3268,
        28182,
        16329,
        9348,
        39,
        12115,
        3336,
        25401,
        309,
        8267,
        3268,
        317,
        376,
        6217,
        32914,
        50,
        34702,
        21725,
        5626,
        3537,
        7125,
        2200,
        38651,
        8845,
        1677,
        3336,
        41067,
        5357,
        3336,
        8782,
        35830,
        371,
        15567,
        1546,
        7655,
        20739,
        21725,
        5626,
        309,
        10206,
        1677,
        15958,
        5357,
        3563,
        18421,
        412,
        10554,
        1137,
        7473,
        6006,
        35238,
        6375,
        327,
        35455,
        370,
        9338,
        6226,
        29089,
        1961,
        33478,
        5161,
        23255,
        53,
        23333,
        3963,
        41670,
        17306,
        3525,
        56,
        6375,
        2320,
        4663,
        9936,
        31515,
        1546,
        28729,
        3336,
        19494,
        2538,
        31404,
        40405,
        50256
    ],
    "metadata": {
        "speaker_id": "2412",
        "chapter_id": "153948",
        "file_id": "2412-153948-0004"
    }
}