{
    "audio_path": "dev-clean\\LibriSpeech\\dev-clean\\251\\137823\\251-137823-0021.flac",
    "text": "MISTER SWIFT CAME INTO THE LIVING ROOM JUST THEN AND TOLD TOM HOW WORRIED MISSUS SWIFT AND SANDY HAD BEEN",
    "tokens": [
        44,
        41517,
        12672,
        32297,
        327,
        10067,
        39319,
        3336,
        406,
        3824,
        2751,
        15107,
        2662,
        25848,
        42243,
        5357,
        309,
        15173,
        41526,
        29630,
        21881,
        7112,
        1961,
        49684,
        2937,
        12672,
        32297,
        5357,
        311,
        6981,
        56,
        367,
        2885,
        9348,
        1677
    ],
    "metadata": {
        "speaker_id": "251",
        "chapter_id": "137823",
        "file_id": "251-137823-0021"
    }
}