{
    "audio_path": "dev-clean\\LibriSpeech\\dev-clean\\2902\\9006\\2902-9006-0008.flac",
    "text": "<|startoftext|> THEY BROUGHT BEFORE THE MINDS OF CHURCHMEN A THOUSAND NEW QUESTIONS WHICH MUST BE SOLVED UNLESS THE CHURCH WAS TO RELINQUISH FOR EVER HER CLAIMS AS THE GREAT TEACHER AND SATISFIER OF THE HUMAN SOUL <|endoftext|>",
    "tokens": [
        50255,
        10970,
        56,
        11177,
        2606,
        38,
        6535,
        38331,
        3336,
        20625,
        5258,
        3963,
        5870,
        4261,
        3398,
        49275,
        317,
        2320,
        20958,
        6981,
        12682,
        43658,
        11053,
        7655,
        20739,
        17191,
        9348,
        36817,
        53,
        1961,
        4725,
        48481,
        3336,
        5870,
        4261,
        3398,
        21725,
        5390,
        29749,
        1268,
        10917,
        18422,
        7473,
        20498,
        24906,
        47666,
        3955,
        50,
        7054,
        3336,
        37853,
        13368,
        16219,
        1137,
        5357,
        29020,
        1797,
        11674,
        1137,
        3963,
        3336,
        45850,
        1565,
        30065,
        43,
        50256
    ],
    "metadata": {
        "speaker_id": "2902",
        "chapter_id": "9006",
        "file_id": "2902-9006-0008"
    }
}