{
    "audio_path": "dev-clean\\LibriSpeech\\dev-clean\\3536\\23268\\3536-23268-0023.flac",
    "text": "<|startoftext|> AFTER A FEW MINUTES PAUSE AND SOME LITTLE EMBARRASSMENT ON THE PART OF MISSUS HORTON AT THE DISAPPOINTMENT SHE HAD TO ENCOUNTER FROM THIS UNEXPECTED DUTIFUL CONDUCT SHE ASKED MISS MILNER IF SHE WOULD NOW HAVE ANY TEA <|endoftext|>",
    "tokens": [
        50255,
        8579,
        5781,
        317,
        376,
        6217,
        20625,
        3843,
        1546,
        8147,
        19108,
        5357,
        41670,
        406,
        22470,
        2538,
        412,
        10744,
        26465,
        10705,
        10979,
        6177,
        3336,
        16652,
        3963,
        49684,
        2937,
        367,
        9863,
        1340,
        5161,
        3336,
        13954,
        2969,
        16402,
        12394,
        10979,
        48052,
        367,
        2885,
        5390,
        412,
        7792,
        19385,
        5781,
        16034,
        12680,
        4725,
        49864,
        9782,
        1961,
        360,
        3843,
        5064,
        6239,
        7102,
        35,
        18415,
        48052,
        7054,
        42,
        1961,
        49684,
        31515,
        21479,
        16876,
        48052,
        370,
        24010,
        20229,
        21515,
        15529,
        13368,
        32,
        50256
    ],
    "metadata": {
        "speaker_id": "3536",
        "chapter_id": "23268",
        "file_id": "3536-23268-0023"
    }
}