{
    "audio_path": "dev-clean\\LibriSpeech\\dev-clean\\3752\\4944\\3752-4944-0042.flac",
    "text": "<|startoftext|> GOOD NIGHT SIR I HOPE YOU WILL BE COMFORTABLE <|endoftext|>",
    "tokens": [
        50255,
        11230,
        3727,
        37707,
        311,
        4663,
        314,
        367,
        32135,
        7013,
        17682,
        9348,
        9440,
        13775,
        38148,
        50256
    ],
    "metadata": {
        "speaker_id": "3752",
        "chapter_id": "4944",
        "file_id": "3752-4944-0042"
    }
}