{
    "audio_path": "dev-clean\\LibriSpeech\\dev-clean\\5694\\64038\\5694-64038-0023.flac",
    "text": "<|startoftext|> THE THIRD DAY IT WAS REPORTED THAT THE YANKEES HAD TAKEN POSITION ON THE MURFREESBORO PIKE <|endoftext|>",
    "tokens": [
        50255,
        10970,
        2320,
        46833,
        24644,
        7283,
        21725,
        39099,
        1961,
        14603,
        3336,
        575,
        1565,
        7336,
        1546,
        367,
        2885,
        309,
        10206,
        1677,
        28069,
        17941,
        6177,
        3336,
        337,
        4261,
        37,
        2200,
        1546,
        33,
        1581,
        46,
        30434,
        7336,
        50256
    ],
    "metadata": {
        "speaker_id": "5694",
        "chapter_id": "64038",
        "file_id": "5694-64038-0023"
    }
}