{
    "audio_path": "dev-clean\\LibriSpeech\\dev-clean\\5895\\34622\\5895-34622-0019.flac",
    "text": "A LOFT UNDER THE ARCH OF THE ROOF CONTAINED THE SCENES AND ON OPENING A TRAP DOOR LAMPS APPEARED PRODUCING WONDERS OF LIGHT",
    "tokens": [
        32,
        17579,
        9792,
        35219,
        3336,
        5923,
        3398,
        3963,
        3336,
        371,
        6684,
        37,
        7102,
        30339,
        1961,
        3336,
        6374,
        1677,
        1546,
        5357,
        6177,
        38303,
        2751,
        317,
        7579,
        2969,
        8410,
        1581,
        406,
        2390,
        3705,
        3486,
        11401,
        1503,
        1961,
        4810,
        3727,
        9598,
        2751,
        370,
        18672,
        4877,
        3963,
        406,
        9947
    ],
    "metadata": {
        "speaker_id": "5895",
        "chapter_id": "34622",
        "file_id": "5895-34622-0019"
    }
}