{
    "audio_path": "dev-clean\\LibriSpeech\\dev-clean\\5895\\34622\\5895-34622-0005.flac",
    "text": "<|startoftext|> THIS GREEN COLOUR HAD SUCCEEDED IN DRAWING ATTENTION TO THE CARRIAGE WHICH WAS KNOWN IN ALL THE FAIR GROUNDS AS THE GREEN BOX <|endoftext|>",
    "tokens": [
        50255,
        43559,
        47606,
        20444,
        11698,
        367,
        2885,
        13558,
        4093,
        41841,
        1961,
        3268,
        360,
        20530,
        2751,
        26195,
        45589,
        5390,
        3336,
        17368,
        49,
        3539,
        8264,
        7655,
        20739,
        21725,
        22466,
        14165,
        3268,
        11096,
        3336,
        9677,
        4663,
        10863,
        19385,
        5258,
        7054,
        3336,
        47606,
        45216,
        50256
    ],
    "metadata": {
        "speaker_id": "5895",
        "chapter_id": "34622",
        "file_id": "5895-34622-0005"
    }
}