{
    "audio_path": "dev-clean\\LibriSpeech\\dev-clean\\6345\\64257\\6345-64257-0011.flac",
    "text": "<|startoftext|> SHE KNEW NOTHING OF THE PLACE HAD NOWHERE TO GO NOWHERE SHE WANTED TO GO HAD NOT A THOUGHT TO TELL HER WHAT QUESTION TO ASK IF SHE MET A LIVING SOUL <|endoftext|>",
    "tokens": [
        50255,
        9693,
        36,
        509,
        13965,
        5626,
        39,
        2751,
        3963,
        3336,
        9297,
        11598,
        367,
        2885,
        20229,
        39,
        9338,
        5390,
        10351,
        20229,
        39,
        9338,
        48052,
        41300,
        1961,
        5390,
        10351,
        367,
        2885,
        5626,
        317,
        2320,
        2606,
        38,
        6535,
        5390,
        13368,
        3069,
        24906,
        25003,
        43658,
        2849,
        5390,
        7054,
        42,
        16876,
        48052,
        31243,
        317,
        406,
        3824,
        2751,
        30065,
        43,
        50256
    ],
    "metadata": {
        "speaker_id": "6345",
        "chapter_id": "64257",
        "file_id": "6345-64257-0011"
    }
}