{
    "audio_path": "dev-clean\\LibriSpeech\\dev-clean\\7850\\73752\\7850-73752-0008.flac",
    "text": "<|startoftext|> FOUR AND TWENTY HOURS AGO AND HE DEEMED HIMSELF THE MOST MISERABLE AND FORLORN OF HUMAN BEINGS AND NOW ALL THE BLESSINGS OF THE WORLD SEEMED SHOWERED AT HIS FEET <|endoftext|>",
    "tokens": [
        50255,
        37,
        11698,
        5357,
        17306,
        3525,
        56,
        29068,
        6998,
        317,
        11230,
        5357,
        11179,
        5550,
        3620,
        1961,
        45909,
        50,
        37738,
        3336,
        337,
        10892,
        50029,
        1137,
        17534,
        5357,
        7473,
        43,
        30649,
        3963,
        45850,
        1565,
        9348,
        20754,
        5357,
        20229,
        11096,
        3336,
        9878,
        7597,
        20754,
        3963,
        3336,
        29564,
        7946,
        3620,
        1961,
        6006,
        36048,
        1961,
        5161,
        33700,
        18630,
        2767,
        50256
    ],
    "metadata": {
        "speaker_id": "7850",
        "chapter_id": "73752",
        "file_id": "7850-73752-0008"
    }
}