{
    "audio_path": "dev-clean\\LibriSpeech\\dev-clean\\7850\\73752\\7850-73752-0001.flac",
    "text": "IN MOMENTS OF DEEP FEELING ALIKE SUDDEN BURSTS OF PROSPERITY AS IN DARKER HOURS MAN MUST BE ALONE",
    "tokens": [
        1268,
        337,
        2662,
        15365,
        3963,
        5550,
        8905,
        18630,
        3698,
        2751,
        8355,
        40,
        7336,
        311,
        8322,
        41819,
        45604,
        2257,
        50,
        3963,
        4810,
        2640,
        18973,
        9050,
        7054,
        3268,
        46455,
        1137,
        29068,
        6998,
        17254,
        17191,
        9348,
        8355,
        11651
    ],
    "metadata": {
        "speaker_id": "7850",
        "chapter_id": "73752",
        "file_id": "7850-73752-0001"
    }
}