{
    "audio_path": "dev-clean\\LibriSpeech\\dev-clean\\84\\121550\\84-121550-0011.flac",
    "text": "NOW HELICON MUST NEEDS POUR FORTH FOR ME AND WITH HER CHOIR URANIA MUST ASSIST ME TO PUT IN VERSE THINGS DIFFICULT TO THINK",
    "tokens": [
        45669,
        36255,
        2149,
        1340,
        17191,
        36465,
        50,
        350,
        11698,
        7473,
        4221,
        7473,
        11948,
        5357,
        13315,
        24906,
        49143,
        4663,
        37902,
        1565,
        3539,
        17191,
        24994,
        8808,
        11948,
        5390,
        350,
        3843,
        3268,
        44156,
        36,
        2320,
        20754,
        360,
        29267,
        2149,
        16724,
        5390,
        2320,
        17248
    ],
    "metadata": {
        "speaker_id": "84",
        "chapter_id": "121550",
        "file_id": "84-121550-0011"
    }
}